ftprelay/__init__.py
ftprelay/relay.py
ftprelay-0.1.dist-info/METADATA
ftprelay-0.1.dist-info/WHEEL
ftprelay-0.1.dist-info/RECORD
