Metadata-Version: 2.1
Name: ftprelay
Version: 0.1
Summary: A framework for mock FTP servers that relay uploaded files
License: MIT
Author: Tomas Bayer
Author-email: mail@tomas.berlin
Requires-Python: >=3.9,<4.0
Classifier: License :: OSI Approved :: MIT License
Classifier: Programming Language :: Python :: 3
Classifier: Programming Language :: Python :: 3.9
Classifier: Programming Language :: Python :: 3.10
Classifier: Programming Language :: Python :: 3.11
Classifier: Programming Language :: Python :: 3.12
Requires-Dist: pyftpdlib (>=1.5.5,<2.0.0)
